ch/__init__.py
ch/debug/__init__.py
ch/debug/gdb_get_trace.py
ch-0.1.2.dist-info/WHEEL
ch-0.1.2.dist-info/METADATA
ch-0.1.2.dist-info/RECORD
